{
  "api": {
    "DemoAmplify": {
      "dependsOn": [
        {
          "attributes": [
            "UserPoolId"
          ],
          "category": "auth",
          "resourceName": "demoamplifyf048c130"
        }
      ],
      "output": {
        "authConfig": {
          "additionalAuthenticationProviders": [],
          "defaultAuthentication": {
            "authenticationType": "AMAZON_COGNITO_USER_POOLS",
            "userPoolConfig": {
              "userPoolId": "authdemoamplifyf048c130"
            }
          }
        }
      },
      "providerPlugin": "awscloudformation",
      "service": "AppSync"
    }
  },
  "auth": {
    "demoamplifyf048c130": {
      "customAuth": false,
      "dependsOn": [],
      "frontendAuthConfig": {
        "mfaConfiguration": "OFF",
        "mfaTypes": [
          "SMS"
        ],
        "passwordProtectionSettings": {
          "passwordPolicyCharacters": [],
          "passwordPolicyMinLength": 8
        },
        "signupAttributes": [],
        "socialProviders": [],
        "usernameAttributes": [],
        "verificationMechanisms": [
          "EMAIL"
        ]
      },
      "providerPlugin": "awscloudformation",
      "service": "Cognito"
    }
  },
  "function": {
    "triggerAutoConfirmAndVerifyUser": {
      "build": true,
      "providerPlugin": "awscloudformation",
      "service": "Lambda"
    }
  }
}